ts_cli/__init__.py
ts_cli/__main__.py
ts_cli/api/__init__.py
ts_cli/commands/config_cmd/__init__.py
ts_cli/commands/init_cmd/__init__.py
ts_cli/commands/init_cmd/files.py
ts_cli/commands/init_cmd/init_artifact_config.py
ts_cli/commands/init_cmd/kinds.py
ts_cli/commands/init_cmd/templates/all-in-one/3.6/README.md.template
ts_cli/commands/init_cmd/templates/data-app/react/4.3/.dockerignore
ts_cli/commands/init_cmd/templates/data-app/react/4.3/.env.example
ts_cli/commands/init_cmd/templates/data-app/react/4.3/.gitignore
ts_cli/commands/init_cmd/templates/data-app/react/4.3/.yarnrc.yml.template
ts_cli/commands/init_cmd/templates/data-app/react/4.3/CONTRIBUTING.md.template
ts_cli/commands/init_cmd/templates/data-app/react/4.3/Dockerfile.template
ts_cli/commands/init_cmd/templates/data-app/react/4.3/README.md.template
ts_cli/commands/init_cmd/templates/data-app/react/4.3/conf/supervisord-local.conf
ts_cli/commands/init_cmd/templates/data-app/react/4.3/conf/supervisord.conf
ts_cli/commands/init_cmd/templates/data-app/react/4.3/images/icon.png
ts_cli/commands/init_cmd/templates/data-app/react/4.3/manifest.json.template
ts_cli/commands/init_cmd/templates/data-app/react/4.3/package.json.template
ts_cli/commands/init_cmd/templates/data-app/react/4.3/packages/client/eslint.config.js
ts_cli/commands/init_cmd/templates/data-app/react/4.3/packages/client/index.html.template
ts_cli/commands/init_cmd/templates/data-app/react/4.3/packages/client/package.json.template
ts_cli/commands/init_cmd/templates/data-app/react/4.3/packages/client/src/App.css
ts_cli/commands/init_cmd/templates/data-app/react/4.3/packages/client/src/App.tsx.template
ts_cli/commands/init_cmd/templates/data-app/react/4.3/packages/client/src/index.css
ts_cli/commands/init_cmd/templates/data-app/react/4.3/packages/client/src/main.tsx
ts_cli/commands/init_cmd/templates/data-app/react/4.3/packages/client/src/vite-env.d.ts
tetrascience_cli-1.7.1.dist-info/METADATA
tetrascience_cli-1.7.1.dist-info/WHEEL
tetrascience_cli-1.7.1.dist-info/entry_points.txt
tetrascience_cli-1.7.1.dist-info/licenses/LICENSE.txt
tetrascience_cli-1.7.1.dist-info/RECORD
