Metadata-Version: 2.4
Name: tetrascience-cli
Version: 1.7.1
Summary: Tetrascience CLI
License: Apache-2.0
License-File: LICENSE.txt
Author: tetrascience
Requires-Python: >=3.9,<4
Classifier: License :: OSI Approved :: Apache Software License
Classifier: Programming Language :: Python :: 3
Classifier: Programming Language :: Python :: 3.9
Classifier: Programming Language :: Python :: 3.10
Classifier: Programming Language :: Python :: 3.11
Classifier: Programming Language :: Python :: 3.12
Classifier: Programming Language :: Python :: 3.13
Classifier: Programming Language :: Python :: 3.14
Provides-Extra: protocol-validation
Requires-Dist: colorama (>=0.4.4,<1)
Requires-Dist: httpx (>=0.25.0,<0.26.0)
Requires-Dist: inquirer (>=3.1.4,<4.0.0)
Requires-Dist: jinja2 (>=3.1.6,<4.0.0)
Requires-Dist: jsonschema (>=3.2.0)
Requires-Dist: packaging (>=25.0,<26.0)
Requires-Dist: pyyaml (>=6.0.1,<7.0.0)
Requires-Dist: requests (>=2.32.4,<3)
Requires-Dist: semver (>=3.0.4,<4.0.0)
Requires-Dist: simplejson (>=3.17.6,<4)
Requires-Dist: toml (>=0.10.2,<0.11.0)
Requires-Dist: tqdm (>=4.67.1,<5.0.0)
Requires-Dist: ts-ids-validator (>=0.10.4)
Requires-Dist: ts-protocol-virtual-machine (>=1.8.3,<2.0.0) ; extra == "protocol-validation"
Requires-Dist: url-normalize (>=2.2.1,<3.0.0)
Project-URL: Homepage, https://developers.tetrascience.com
